lconrg/.python-version
lconrg/__init__.py
lconrg/lconrg.py
lconrg-2024.5.26.dist-info/LICENSE
lconrg-2024.5.26.dist-info/METADATA
lconrg-2024.5.26.dist-info/WHEEL
lconrg-2024.5.26.dist-info/RECORD
