Metadata-Version: 2.1
Name: lconrg
Version: 2024.5.26
Summary: 
Author: Your Name
Author-email: you@example.com
Requires-Python: >=3.9,<3.11
Classifier: Programming Language :: Python :: 3
Classifier: Programming Language :: Python :: 3.9
Classifier: Programming Language :: Python :: 3.10
Requires-Dist: numpy (>=1.22,<2.0)
Requires-Dist: pandas (>=1.4.1,<2.0.0)
